[
  {"letra": "A", "pregunta": "Empieza por A: Continente helado en el polo sur.", "respuesta": "Antartida"},
  {"letra": "B", "pregunta": "Empieza por B: Baile clásico que requiere mucha disciplina y puntas de pie.", "respuesta": "Ballet"},
  {"letra": "C", "pregunta": "Empieza por C: Animal del desierto con jorobas.", "respuesta": "Camello"},
  {"letra": "D", "pregunta": "Empieza por D: Piedra preciosa más dura que existe.", "respuesta": "Diamante"},
  {"letra": "E", "pregunta": "Empieza por E: País europeo con forma de bota.", "respuesta": "Italia"},
  {"letra": "F", "pregunta": "Empieza por F: Hongo comestible o venenoso.", "respuesta": "Seta"},
  {"letra": "G", "pregunta": "Empieza por G: Gigante mitológico con un solo ojo.", "respuesta": "Ciclope"},
  {"letra": "H", "pregunta": "Empieza por H: Personaje de ficción, mago joven con una cicatriz en la frente.", "respuesta": "Harry Potter"},
  {"letra": "I", "pregunta": "Empieza por I: Isla famosa de Chile con estatuas gigantes llamadas Moáis.", "respuesta": "Pascua"},
  {"letra": "J", "pregunta": "Empieza por J: Deporte olímpico de lucha de origen japonés.", "respuesta": "Judo"},
  {"letra": "K", "pregunta": "Empieza por K: Salsa de tomate dulce y vinagre.", "respuesta": "Ketchup"},
  {"letra": "L", "pregunta": "Empieza por L: Mamífero que aulla a la luna.", "respuesta": "Lobo"},
  {"letra": "M", "pregunta": "Empieza por M: Planeta rojo del sistema solar.", "respuesta": "Marte"},
  {"letra": "N", "pregunta": "Empieza por N: Fenómeno meteorológico que consiste en cristales de hielo que caen del cielo.", "respuesta": "Nieve"},
  {"letra": "Ñ", "pregunta": "Contiene la Ñ: Dedo más pequeño de la mano.", "respuesta": "Meñique"},
  {"letra": "O", "pregunta": "Empieza por O: Órgano del cuerpo que bombea sangre.", "respuesta": "Corazon"},
  {"letra": "P", "pregunta": "Empieza por P: Personaje de madera al que le crecía la nariz si mentía.", "respuesta": "Pinocho"},
  {"letra": "Q", "pregunta": "Empieza por Q: Medida de peso equivalente a 100 kilogramos (antigua).", "respuesta": "Quintal"},
  {"letra": "R", "pregunta": "Empieza por R: Color que indica 'pare' en los semáforos.", "respuesta": "Rojo"},
  {"letra": "S", "pregunta": "Empieza por S: Reptil largo y sin patas.", "respuesta": "Serpiente"},
  {"letra": "T", "pregunta": "Empieza por T: Bebida caliente hecha con hojas secas.", "respuesta": "Te"},
  {"letra": "U", "pregunta": "Empieza por U: Objeto que se usa para pintar las uñas.", "respuesta": "Esmalte"},
  {"letra": "V", "pregunta": "Empieza por V: Estación del año más calurosa.", "respuesta": "Verano"},
  {"letra": "W", "pregunta": "Empieza por W: Red informática mundial (World Wide Web).", "respuesta": "Web"},
  {"letra": "X", "pregunta": "Contiene la X: Vehículo de transporte público individual.", "respuesta": "Taxi"},
  {"letra": "Y", "pregunta": "Empieza por Y: Parte amarilla del huevo.", "respuesta": "Yema"},
  {"letra": "Z", "pregunta": "Empieza por Z: Animal rayado parecido al caballo.", "respuesta": "Cebra"}
]